{
	"name": "Streadata.io API Gallery - Knoema",
	"description": "This is a repository of knoema APIs, self-contained as a Github repository, with HTML and YAML representations of the APIs and their surrounding operations.",
	"image": "http://template.streamdata.gallery/assets/knoema.png",
	"created": "2018-02-24",
	"modified": "2018-08-30",
	"url": "http://knoema.streamdata.gallery/apis.json",
	"specificationVersion": "0.14",
	"apis": [
		{
			"name": "Knoema",
			"x-api-slug": "knoema",
			"description": "Knoema is the free to use public and open data platform for users with interests in statistics and data analysis, visual storytelling and making infographics and data-driven presentations",
			"image": "http://kinlane-productions.s3.amazonaws.com/api-evangelist-site/company/logos/knoema-logo.jpg",
			"humanURL": "https://knoema.com",
			"baseURL": "http://knoema.com//api/1.0",
			"tags": "Knoema",
			"properties": [
				{
					"type": "x-openapi-spec",
					"url": "https://raw.githubusercontent.com/streamdata-gallery-organizations/knoema/master/_listings/knoema/openapi.md"
				}
			]
		}
	],
	"tags": "Knoema",
	"include": [
		{
			"name": "Knoema",
			"url": "https://raw.githubusercontent.com/streamdata-gallery-organizations/knoema/master/_listings/knoema/apis.yaml"
		}
	]
}